<?xml version="1.0" encoding="UTF-8" standalone="yes"?>
<w:hdr xmlns:wpc="http://schemas.microsoft.com/office/word/2010/wordprocessingCanvas" xmlns:cx="http://schemas.microsoft.com/office/drawing/2014/chartex" xmlns:cx1="http://schemas.microsoft.com/office/drawing/2015/9/8/chartex" xmlns:cx2="http://schemas.microsoft.com/office/drawing/2015/10/21/chartex" xmlns:cx3="http://schemas.microsoft.com/office/drawing/2016/5/9/chartex" xmlns:cx4="http://schemas.microsoft.com/office/drawing/2016/5/10/chartex" xmlns:cx5="http://schemas.microsoft.com/office/drawing/2016/5/11/chartex" xmlns:cx6="http://schemas.microsoft.com/office/drawing/2016/5/12/chartex" xmlns:cx7="http://schemas.microsoft.com/office/drawing/2016/5/13/chartex" xmlns:cx8="http://schemas.microsoft.com/office/drawing/2016/5/14/chartex" xmlns:mc="http://schemas.openxmlformats.org/markup-compatibility/2006" xmlns:aink="http://schemas.microsoft.com/office/drawing/2016/ink" xmlns:am3d="http://schemas.microsoft.com/office/drawing/2017/model3d" xmlns:o="urn:schemas-microsoft-com:office:office" xmlns:oel="http://schemas.microsoft.com/office/2019/extlst" xmlns:r="http://schemas.openxmlformats.org/officeDocument/2006/relationships" xmlns:m="http://schemas.openxmlformats.org/officeDocument/2006/math" xmlns:v="urn:schemas-microsoft-com:vml" xmlns:wp14="http://schemas.microsoft.com/office/word/2010/wordprocessingDrawing" xmlns:wp="http://schemas.openxmlformats.org/drawingml/2006/wordprocessingDrawing" xmlns:w10="urn:schemas-microsoft-com:office:word" xmlns:w="http://schemas.openxmlformats.org/wordprocessingml/2006/main" xmlns:w14="http://schemas.microsoft.com/office/word/2010/wordml" xmlns:w15="http://schemas.microsoft.com/office/word/2012/wordml" xmlns:w16cex="http://schemas.microsoft.com/office/word/2018/wordml/cex" xmlns:w16cid="http://schemas.microsoft.com/office/word/2016/wordml/cid" xmlns:w16="http://schemas.microsoft.com/office/word/2018/wordml" xmlns:w16du="http://schemas.microsoft.com/office/word/2023/wordml/word16du" xmlns:w16sdtdh="http://schemas.microsoft.com/office/word/2020/wordml/sdtdatahash" xmlns:w16sdtfl="http://schemas.microsoft.com/office/word/2024/wordml/sdtformatlock" xmlns:w16se="http://schemas.microsoft.com/office/word/2015/wordml/symex" xmlns:wpg="http://schemas.microsoft.com/office/word/2010/wordprocessingGroup" xmlns:wpi="http://schemas.microsoft.com/office/word/2010/wordprocessingInk" xmlns:wne="http://schemas.microsoft.com/office/word/2006/wordml" xmlns:wps="http://schemas.microsoft.com/office/word/2010/wordprocessingShape" mc:Ignorable="w14 w15 w16se w16cid w16 w16cex w16sdtdh w16sdtfl w16du wp14"><w:tbl><w:tblPr><w:tblW w:w="5009" w:type="pct"/><w:tblInd w:w="-5" w:type="dxa"/><w:tblLook w:val="0600" w:firstRow="0" w:lastRow="0" w:firstColumn="0" w:lastColumn="0" w:noHBand="1" w:noVBand="1"/></w:tblPr><w:tblGrid><w:gridCol w:w="1701"/><w:gridCol w:w="7067"/><w:gridCol w:w="1707"/></w:tblGrid><w:tr w:rsidR="00E14DC9" w:rsidRPr="009678B1" w14:paraId="2C574FD6" w14:textId="77777777" w:rsidTr="00CF5DA3"><w:trPr><w:trHeight w:val="1567"/></w:trPr><w:tc><w:tcPr><w:tcW w:w="1701" w:type="dxa"/><w:tcBorders><w:top w:val="single" w:sz="4" w:space="0" w:color="auto"/><w:left w:val="single" w:sz="4" w:space="0" w:color="auto"/><w:bottom w:val="single" w:sz="4" w:space="0" w:color="auto"/><w:right w:val="nil"/></w:tcBorders><w:shd w:val="clear" w:color="auto" w:fill="CBEDFD"/></w:tcPr><w:p w14:paraId="4588A7E1" w14:textId="77777777" w:rsidR="00E14DC9" w:rsidRPr="009678B1" w:rsidRDefault="00E14DC9" w:rsidP="00E14DC9"><w:pPr><w:tabs><w:tab w:val="right" w:pos="10239"/></w:tabs><w:rPr><w:rFonts w:asciiTheme="minorBidi" w:hAnsiTheme="minorBidi"/><w:bCs/><w:sz w:val="16"/><w:szCs w:val="16"/></w:rPr></w:pPr><w:r w:rsidRPr="009678B1"><w:rPr><w:rFonts w:asciiTheme="minorBidi" w:hAnsiTheme="minorBidi"/><w:bCs/><w:noProof/><w:sz w:val="16"/><w:szCs w:val="16"/></w:rPr><w:drawing><wp:anchor distT="0" distB="0" distL="114300" distR="114300" simplePos="0" relativeHeight="251663360" behindDoc="0" locked="0" layoutInCell="1" allowOverlap="1" wp14:anchorId="2C9E7F90" wp14:editId="57908157"><wp:simplePos x="0" y="0"/><wp:positionH relativeFrom="column"><wp:posOffset>-60921</wp:posOffset></wp:positionH><wp:positionV relativeFrom="paragraph"><wp:posOffset>4484</wp:posOffset></wp:positionV><wp:extent cx="1035685" cy="885190"/><wp:effectExtent l="0" t="0" r="0" b="0"/><wp:wrapNone/><wp:docPr id="1241841499" name="Picture 3" descr="A red and blue logo with a flower&#xA;&#xA;Description automatically generated"/><wp:cNvGraphicFramePr><a:graphicFrameLocks xmlns:a="http://schemas.openxmlformats.org/drawingml/2006/main" noChangeAspect="1"/></wp:cNvGraphicFramePr><a:graphic xmlns:a="http://schemas.openxmlformats.org/drawingml/2006/main"><a:graphicData uri="http://schemas.openxmlformats.org/drawingml/2006/picture"><pic:pic xmlns:pic="http://schemas.openxmlformats.org/drawingml/2006/picture"><pic:nvPicPr><pic:cNvPr id="106652839" name="Picture 3" descr="A red and blue logo with a flower&#xA;&#xA;Description automatically generated"/><pic:cNvPicPr/></pic:nvPicPr><pic:blipFill><a:blip r:embed="rId1" cstate="print"><a:extLst><a:ext uri="{28A0092B-C50C-407E-A947-70E740481C1C}"><a14:useLocalDpi xmlns:a14="http://schemas.microsoft.com/office/drawing/2010/main" val="0"/></a:ext></a:extLst></a:blip><a:stretch><a:fillRect/></a:stretch></pic:blipFill><pic:spPr><a:xfrm><a:off x="0" y="0"/><a:ext cx="1035685" cy="885190"/></a:xfrm><a:prstGeom prst="rect"><a:avLst/></a:prstGeom></pic:spPr></pic:pic></a:graphicData></a:graphic><wp14:sizeRelH relativeFrom="margin"><wp14:pctWidth>0</wp14:pctWidth></wp14:sizeRelH><wp14:sizeRelV relativeFrom="margin"><wp14:pctHeight>0</wp14:pctHeight></wp14:sizeRelV></wp:anchor></w:drawing></w:r><w:r w:rsidRPr="009678B1"><w:rPr><w:rFonts w:asciiTheme="minorBidi" w:hAnsiTheme="minorBidi"/><w:sz w:val="16"/><w:szCs w:val="16"/></w:rPr><w:t xml:space="preserve">                                                                         </w:t></w:r></w:p></w:tc><w:tc><w:tcPr><w:tcW w:w="7067" w:type="dxa"/><w:tcBorders><w:top w:val="single" w:sz="4" w:space="0" w:color="auto"/><w:left w:val="nil"/><w:bottom w:val="single" w:sz="4" w:space="0" w:color="auto"/><w:right w:val="nil"/></w:tcBorders><w:vAlign w:val="center"/></w:tcPr><w:p w14:paraId="269D33F6" w14:textId="77777777" w:rsidR="00E14DC9" w:rsidRPr="009678B1" w:rsidRDefault="00000000" w:rsidP="00E14DC9"><w:pPr><w:tabs><w:tab w:val="right" w:pos="10239"/></w:tabs><w:jc w:val="center"/><w:rPr><w:rFonts w:asciiTheme="minorBidi" w:hAnsiTheme="minorBidi"/><w:b/><w:bCs/><w:sz w:val="32"/><w:szCs w:val="32"/></w:rPr></w:pPr><w:sdt><w:sdtPr><w:rPr><w:rFonts w:asciiTheme="minorBidi" w:hAnsiTheme="minorBidi"/><w:b/><w:bCs/><w:sz w:val="32"/><w:szCs w:val="32"/></w:rPr><w:alias w:val="RTO"/><w:tag w:val="RTO"/><w:id w:val="1398478418"/><w:placeholder><w:docPart w:val="54DA1D8003F243468A501DB49319B455"/></w:placeholder><w:dataBinding w:prefixMappings="xmlns:ns0='http://schemas.microsoft.com/office/2006/metadata/properties' xmlns:ns1='http://www.w3.org/2001/XMLSchema-instance' xmlns:ns2='http://schemas.microsoft.com/office/infopath/2007/PartnerControls' xmlns:ns3='2d7a8bbf-693f-43b0-8275-6b167627f7a7' xmlns:ns4='c8db29e5-cdb3-4545-b361-fadf9f25db7c' " w:xpath="/ns0:properties[1]/documentManagement[1]/ns3:RTO[1]" w:storeItemID="{99CB991B-863D-48D2-AEBC-AEB6F0AC7AE5}"/><w:text/></w:sdtPr><w:sdtContent><w:r w:rsidR="00E14DC9" w:rsidRPr="009678B1"><w:rPr><w:rFonts w:asciiTheme="minorBidi" w:hAnsiTheme="minorBidi"/><w:b/><w:bCs/><w:sz w:val="32"/><w:szCs w:val="32"/></w:rPr><w:t>NSW Department of Education 90333</w:t></w:r></w:sdtContent></w:sdt></w:p><w:p w14:paraId="77DF3A4F" w14:textId="77777777" w:rsidR="00E14DC9" w:rsidRPr="009678B1" w:rsidRDefault="00E14DC9" w:rsidP="00E14DC9"><w:pPr><w:tabs><w:tab w:val="right" w:pos="10239"/></w:tabs><w:jc w:val="center"/><w:rPr><w:rFonts w:asciiTheme="minorBidi" w:hAnsiTheme="minorBidi"/><w:b/><w:bCs/><w:sz w:val="28"/><w:szCs w:val="28"/></w:rPr></w:pPr></w:p><w:p w14:paraId="49CCCFA7" w14:textId="77777777" w:rsidR="00E14DC9" w:rsidRPr="009678B1" w:rsidRDefault="00E14DC9" w:rsidP="00E14DC9"><w:pPr><w:tabs><w:tab w:val="right" w:pos="10239"/></w:tabs><w:jc w:val="center"/><w:rPr><w:rFonts w:asciiTheme="minorBidi" w:hAnsiTheme="minorBidi"/><w:b/><w:bCs/><w:sz w:val="28"/><w:szCs w:val="28"/></w:rPr></w:pPr></w:p></w:tc><w:tc><w:tcPr><w:tcW w:w="1707" w:type="dxa"/><w:tcBorders><w:top w:val="single" w:sz="4" w:space="0" w:color="auto"/><w:left w:val="nil"/><w:bottom w:val="single" w:sz="4" w:space="0" w:color="auto"/><w:right w:val="single" w:sz="4" w:space="0" w:color="auto"/></w:tcBorders></w:tcPr><w:p w14:paraId="51470352" w14:textId="77777777" w:rsidR="00E14DC9" w:rsidRPr="009678B1" w:rsidRDefault="00E14DC9" w:rsidP="00E14DC9"><w:pPr><w:tabs><w:tab w:val="right" w:pos="10239"/></w:tabs><w:rPr><w:rFonts w:asciiTheme="minorBidi" w:hAnsiTheme="minorBidi"/><w:bCs/><w:sz w:val="16"/><w:szCs w:val="16"/></w:rPr></w:pPr><w:r w:rsidRPr="009678B1"><w:rPr><w:rFonts w:asciiTheme="minorBidi" w:hAnsiTheme="minorBidi"/><w:bCs/><w:noProof/><w:sz w:val="16"/><w:szCs w:val="16"/></w:rPr><w:drawing><wp:anchor distT="0" distB="0" distL="114300" distR="114300" simplePos="0" relativeHeight="251662336" behindDoc="0" locked="0" layoutInCell="1" allowOverlap="1" wp14:anchorId="5DBED220" wp14:editId="7C900890"><wp:simplePos x="0" y="0"/><wp:positionH relativeFrom="column"><wp:posOffset>-17145</wp:posOffset></wp:positionH><wp:positionV relativeFrom="paragraph"><wp:posOffset>20209</wp:posOffset></wp:positionV><wp:extent cx="1009650" cy="965835"/><wp:effectExtent l="0" t="0" r="0" b="5715"/><wp:wrapNone/><wp:docPr id="469855488" name="Picture 4" descr="Worker typing on laptop"/><wp:cNvGraphicFramePr><a:graphicFrameLocks xmlns:a="http://schemas.openxmlformats.org/drawingml/2006/main" noChangeAspect="1"/></wp:cNvGraphicFramePr><a:graphic xmlns:a="http://schemas.openxmlformats.org/drawingml/2006/main"><a:graphicData uri="http://schemas.openxmlformats.org/drawingml/2006/picture"><pic:pic xmlns:pic="http://schemas.openxmlformats.org/drawingml/2006/picture"><pic:nvPicPr><pic:cNvPr id="1589393669" name="Picture 1589393669" descr="Worker typing on laptop"/><pic:cNvPicPr/></pic:nvPicPr><pic:blipFill><a:blip r:embed="rId2" cstate="print"><a:extLst><a:ext uri="{28A0092B-C50C-407E-A947-70E740481C1C}"><a14:useLocalDpi xmlns:a14="http://schemas.microsoft.com/office/drawing/2010/main" val="0"/></a:ext></a:extLst></a:blip><a:stretch><a:fillRect/></a:stretch></pic:blipFill><pic:spPr><a:xfrm><a:off x="0" y="0"/><a:ext cx="1009650" cy="965835"/></a:xfrm><a:prstGeom prst="rect"><a:avLst/></a:prstGeom></pic:spPr></pic:pic></a:graphicData></a:graphic><wp14:sizeRelH relativeFrom="margin"><wp14:pctWidth>0</wp14:pctWidth></wp14:sizeRelH><wp14:sizeRelV relativeFrom="margin"><wp14:pctHeight>0</wp14:pctHeight></wp14:sizeRelV></wp:anchor></w:drawing></w:r></w:p></w:tc></w:tr></w:tbl><w:p w14:paraId="2E303371" w14:textId="77777777" w:rsidR="00A85B7E" w:rsidRDefault="00A85B7E"><w:pPr><w:pStyle w:val="Header"/></w:pPr></w:p></w:hdr>